st_combobox/__init__.py
st_combobox/frontend/build/asset-manifest.json
st_combobox/frontend/build/bootstrap.min.css
st_combobox/frontend/build/index.html
st_combobox/frontend/build/precache-manifest.da95221f85175e6df53938afa64e861a.js
st_combobox/frontend/build/service-worker.js
st_combobox/frontend/build/static/js/2.7b601a3e.chunk.js
st_combobox/frontend/build/static/js/2.7b601a3e.chunk.js.LICENSE.txt
st_combobox/frontend/build/static/js/2.7b601a3e.chunk.js.map
st_combobox/frontend/build/static/js/main.70ce7f5a.chunk.js
st_combobox/frontend/build/static/js/main.70ce7f5a.chunk.js.map
st_combobox/frontend/build/static/js/runtime-main.1401e97d.js
st_combobox/frontend/build/static/js/runtime-main.1401e97d.js.map
st_combobox/frontend/build/static/media/st-arrow.9f06d2cd.svg
st_combobox/frontend/build/static/media/st-clear.45da9505.svg
st_combobox-1.2.0.dist-info/LICENSE
st_combobox-1.2.0.dist-info/METADATA
st_combobox-1.2.0.dist-info/WHEEL
st_combobox-1.2.0.dist-info/top_level.txt
st_combobox-1.2.0.dist-info/RECORD
