Metadata-Version: 2.1
Name: st-combobox
Version: 1.2.0
Summary: Streamlit AutoComplete ComboBox
Home-page: https://github.com/hoggatt/st-combobox
Author: hoggatt
License: MIT
Project-URL: Source Code, https://github.com/hoggatt/st-combobox
Requires-Python: >=3.7
License-File: LICENSE
Requires-Dist: streamlit >=1.27.0
Provides-Extra: dev
Requires-Dist: black ; extra == 'dev'
Requires-Dist: isort ; extra == 'dev'
Requires-Dist: ruff ; extra == 'dev'
Provides-Extra: tests
Requires-Dist: wikipedia ; extra == 'tests'
